hirezapi/HiRezAPI.py
hirezapi/PaladinsAPI.py
hirezapi/RealmsAPI.py
hirezapi/SmiteAPI.py
hirezapi/__init__.py
hirezapi/__main__.py
hirezapi/cli.py
hirezapi/enums/Endpoints.py
hirezapi/enums/Languages.py
hirezapi/enums/Queue.py
hirezapi/enums/ResponseFormat.py
hirezapi/enums/__init__.py
hirezapi-0.0.2.dist-info/AUTHORS.rst
hirezapi-0.0.2.dist-info/LICENSE
hirezapi-0.0.2.dist-info/METADATA
hirezapi-0.0.2.dist-info/WHEEL
hirezapi-0.0.2.dist-info/entry_points.txt
hirezapi-0.0.2.dist-info/top_level.txt
hirezapi-0.0.2.dist-info/RECORD
