Metadata-Version: 2.1
Name: hirezapi
Version: 0.0.2
Summary: An example package. Generated with cookiecutter-pylibrary.
Home-page: https://github.com/AidanJohnston/hirezapi
Author: Aidan Johnston
Author-email: contact@aidanjohnston.ca
License: MIT
Project-URL: Documentation, https://hirezapi.readthedocs.io/
Project-URL: Changelog, https://hirezapi.readthedocs.io/en/latest/changelog.html
Project-URL: Issue Tracker, https://github.com/AidanJohnston/hirezapi/issues
Classifier: Development Status :: 3 - Alpha
Classifier: Intended Audience :: Developers
Classifier: License :: OSI Approved :: MIT License
Classifier: Operating System :: Unix
Classifier: Operating System :: POSIX
Classifier: Operating System :: Microsoft :: Windows
Classifier: Programming Language :: Python
Classifier: Programming Language :: Python :: 3
Classifier: Programming Language :: Python :: 3 :: Only
Classifier: Programming Language :: Python :: 3.7
Classifier: Programming Language :: Python :: 3.8
Classifier: Programming Language :: Python :: 3.9
Classifier: Programming Language :: Python :: 3.10
Classifier: Programming Language :: Python :: 3.11
Classifier: Programming Language :: Python :: Implementation :: CPython
Classifier: Programming Language :: Python :: Implementation :: PyPy
Classifier: Topic :: Utilities
Requires-Python: >=3.7
License-File: LICENSE
License-File: AUTHORS.rst
Requires-Dist: requests
